recast_workflow/__init__.py
recast_workflow/catalogue.py
recast_workflow/common_inputs.yml
recast_workflow/definitions.py
recast_workflow/inventory.py
recast_workflow/scan.py
recast_workflow/utils.py
recast_workflow/workflow.py
recast_workflow/cli/__init__.py
recast_workflow/cli/cli.py
recast_workflow/cli/complete.py
recast_workflow/cli/inv.py
recast_workflow/cli/make.py
recast_workflow/cli/scan.py
recast_workflow/images/__init__.py
recast_workflow/images/build_utils.py
recast_workflow/images/contur/Dockerfile
recast_workflow/images/madanalysis/Dockerfile
recast_workflow/images/madanalysis/installer.sh
recast_workflow/images/madanalysis/ma5_install.dat
recast_workflow/images/madgraph_pythia/madgraph/Dockerfile
recast_workflow/images/madgraph_pythia/madgraph/steer_madgraph.py
recast_workflow/images/madgraph_pythia/pythia/Dockerfile
recast_workflow/images/madgraph_pythia/pythia/README
recast_workflow/images/madgraph_pythia/pythia/steer_pythia.py
recast_workflow/images/pyhf/Dockerfile
recast_workflow/images/pyhf/build.sh
recast_workflow/images/pyhf/make_patch.py
recast_workflow/images/rivet/Dockerfile
recast_workflow/images/rivet/build.sh
recast_workflow/images/rivet/output.yoda
recast_workflow/images/rivet/test.json
recast_workflow/images/rivet/yoda2json.py
recast_workflow/interfaces/hepmc.yml
recast_workflow/interfaces/yoda.yml
recast_workflow/subworkflows/analysis/madanalysis/common_inputs.py
recast_workflow/subworkflows/analysis/madanalysis/description.yml
recast_workflow/subworkflows/analysis/madanalysis/step.yml
recast_workflow/subworkflows/analysis/madanalysis/workflow.yml
recast_workflow/subworkflows/generation/madgraph_pythia/description.yml
recast_workflow/subworkflows/generation/madgraph_pythia/madgraph.yml
recast_workflow/subworkflows/generation/madgraph_pythia/pythia.yml
recast_workflow/subworkflows/generation/madgraph_pythia/workflow.yml
recast_workflow/subworkflows/selection/rivet/__init__.py
recast_workflow/subworkflows/selection/rivet/common_inputs.py
recast_workflow-1.0.2.dist-info/METADATA
recast_workflow-1.0.2.dist-info/WHEEL
recast_workflow-1.0.2.dist-info/entry_points.txt
recast_workflow-1.0.2.dist-info/top_level.txt
recast_workflow-1.0.2.dist-info/RECORD
